.gitignore
HISTORY.md
LICENSE
README.md
setup.py
django_profiling.egg-info/PKG-INFO
django_profiling.egg-info/SOURCES.txt
django_profiling.egg-info/dependency_links.txt
django_profiling.egg-info/not-zip-safe
django_profiling.egg-info/requires.txt
django_profiling.egg-info/top_level.txt
dprofiling/__init__.py
dprofiling/admin.py
dprofiling/forms.py
dprofiling/middleware.py
dprofiling/models.py
dprofiling/signals.py
dprofiling/backends/__init__.py
dprofiling/backends/db.py
dprofiling/fixtures/dprofiling/test.json
dprofiling/templates/admin/dprofiling/session/stats_form.html
dprofiling/tests/__init__.py
dprofiling/tests/urls.py
dprofiling/tests/views.py
dprofiling/tests/backends/__init__.py
dprofiling/tests/backends/db.py