Metadata-Version: 1.1
Name: django-profiling
Version: 0.1
Summary: Django Profiling
Home-page: https://github.com/TAMUArch/django-profiling
Author: Texas A&M University, College of Architecture
Author-email: webadmin@arch.tamu.edu
License: UNKNOWN
Keywords: django profiling
Platform: UNKNOWN
Classifier: Framework :: Django
Classifier: Development Status :: 4 - Beta
Classifier: Programming Language :: Python
Classifier: Topic :: Software Development :: Libraries :: Python Modules
Classifier: License :: OSI Approved :: Apache Software License
